deeptree/__init__.py
deeptree/decision_tree_classifier.py
deeptree-0.0.2.dist-info/METADATA
deeptree-0.0.2.dist-info/WHEEL
deeptree-0.0.2.dist-info/licenses/LICENSE.txt
deeptree-0.0.2.dist-info/RECORD
