Metadata-Version: 2.1
Name: deeptree
Version: 0.0.2
Summary: Decision tree classifier implemented using gini index splitting
Project-URL: Homepage, https://github.com/a-abrhm/deeptree
Project-URL: Bug Tracker, https://github.com/a-abrhm/deeptree/issues
Author-email: Alan Abraham <alan.abraham.tm@gmail.com>
License: MIT License
License-File: LICENSE.txt
Keywords: CART,classifier,continuous features,decision tree,discrete features,gini index,no dependencies
Classifier: License :: OSI Approved :: MIT License
Classifier: Operating System :: OS Independent
Classifier: Programming Language :: Python :: 3
Requires-Python: >=3.7
